<mission>
  <object_type>Product_Mission_PDS3</object_type>
  <column>
    <name>identifier</name>
    <type>attribute</type>
    <value>null</value>
  </column>
  <column>
    <name>title</name>
    <type>attribute</type>
    <value>null</value>
  </column>
  <column>
    <name>format</name>
    <type>out</type>
    <value>XML</value>
  </column>
  <column>
    <name>description</name>
    <type>slot</type>
    <value>mission_description</value>
  </column>
  <column>
    <name>language</name>
    <type>out</type>
    <value>en</value>
  </column>
  <column>
    <name>publisher</name>
    <type>out</type>
    <value>NASA.PDS</value>
  </column>
  <column>
    <name>resContext</name>
    <type>out</type>
    <value>NASA.PDS</value>
  </column>
  <column>
    <name>resClass</name>
    <type>out</type>
    <value>metadata.mission</value>
  </column>
  <column>
    <name>resLocation</name>
    <type>out</type>
    <value>http://starbrite.jpl.nasa.gov/pds/viewMissionProfile.jsp?MISSION_NAME={mission_name}</value>
  </column>
  <column>
    <name>mission_name</name>
    <type>slot</type>
    <value>mission_name</value>
  </column>
  <column>
    <name>mission_name_or_alias</name>
    <type>slot</type>
    <value>alternate_title</value>
  </column>
  <column>
    <name>mission_start_date</name>
    <type>slot</type>
    <value>mission_start_date</value>
  </column>
  <column>
    <name>mission_stop_date</name>
    <type>slot</type>
    <value>mission_stop_date</value>
  </column>
  <column>
    <name>mission_desc</name>
    <type>slot</type>
    <value>mission_description</value>
  </column>
  <column>
    <name>mission_objectives_summary</name>
    <type>slot</type>
    <value>mission_objectives_summary</value>
  </column>
  <column>
    <name>resource_class</name>
    <type>out</type>
    <value>Mission_Description</value>
  </column>
</mission>